setup.py
distributions_p1/Binomialdistribution.py
distributions_p1/Gaussiandistribution.py
distributions_p1/Generaldistribution.py
distributions_p1/__init__.py
distributions_p1.egg-info/PKG-INFO
distributions_p1.egg-info/SOURCES.txt
distributions_p1.egg-info/dependency_links.txt
distributions_p1.egg-info/not-zip-safe
distributions_p1.egg-info/top_level.txt